moltbook_poster/__init__.py
moltbook_poster/poster.py
moltbook_poster-0.1.0.dist-info/METADATA
moltbook_poster-0.1.0.dist-info/WHEEL
moltbook_poster-0.1.0.dist-info/entry_points.txt
moltbook_poster-0.1.0.dist-info/top_level.txt
moltbook_poster-0.1.0.dist-info/RECORD
