Metadata-Version: 2.4
Name: moltbook-poster
Version: 0.1.0
Summary: AI-powered Moltbook automation - analyzes GitHub PRs and posts technical summaries
Author-email: jleechan <jlee@jleechan.org>
License-Expression: MIT
Project-URL: Homepage, https://github.com/jleechanorg/worldarchitect.ai
Project-URL: Repository, https://github.com/jleechanorg/worldarchitect.ai
Project-URL: Issues, https://github.com/jleechanorg/worldarchitect.ai/issues
Keywords: moltbook,ai,automation,github,claude,llm
Classifier: Development Status :: 4 - Beta
Classifier: Intended Audience :: Developers
Classifier: Programming Language :: Python :: 3
Classifier: Programming Language :: Python :: 3.11
Classifier: Programming Language :: Python :: 3.12
Classifier: Topic :: Software Development :: Libraries :: Python Modules
Classifier: Topic :: Communications
Requires-Python: >=3.11
Provides-Extra: dev
Requires-Dist: pytest>=7.0.0; extra == "dev"
Requires-Dist: black>=22.0.0; extra == "dev"
Requires-Dist: ruff>=0.1.0; extra == "dev"
